setup.cfg
setup.py
dbbkp/__init__.py
dbbkp/array.py
dbbkp/main.py
dbbkp.egg-info/PKG-INFO
dbbkp.egg-info/SOURCES.txt
dbbkp.egg-info/dependency_links.txt
dbbkp.egg-info/not-zip-safe
dbbkp.egg-info/requires.txt
dbbkp.egg-info/top_level.txt
dbbkp/engines/__init__.py
dbbkp/engines/dsDefault.py
dbbkp/engines/dsDefault2.py
dbbkp/engines/formatter.py
dbbkp/engines/fsDefault.py
dbbkp/engines/mongoDocker.py
dbbkp/engines/mysqlDefault.py
dbbkp/engines/mysqlDocker.py
dbbkp/engines/mysqlDocker2.py
dbbkp/engines/scripts.py
dbbkp/engines/svrDefault.py
dbbkp/engines/vsDefault.py
dbbkp/utils/gitlab.py