Metadata-Version: 2.1
Name: dbbkp
Version: 0.1.23
Summary: dbbkp Package
Requires-Dist: numpy
Requires-Dist: pandas
Requires-Dist: matplotlib
Requires-Dist: utilum
Requires-Dist: sql_formatter
